new_natnet_client/__init__.py
new_natnet_client/Client.py
new_natnet_client/NatNetTypes.py
new_natnet_client/Unpackers.py
new_natnet_client-6.0.1.dist-info/LICENSE
new_natnet_client-6.0.1.dist-info/METADATA
new_natnet_client-6.0.1.dist-info/WHEEL
new_natnet_client-6.0.1.dist-info/RECORD
