Metadata-Version: 2.1
Name: new-natnet-client
Version: 6.0.1
Summary: natnet client for motive applications with pure python
Home-page: https://optitrack.com/
License: GLWTPL
Author: Ignacio de la Torre Arias
Author-email: ignaciodlta@gmail.com
Maintainer: Ignacio de la Torre Arias
Maintainer-email: ignaciodlta@gmail.com
Requires-Python: >=3.12,<4.0
Classifier: Development Status :: 5 - Production/Stable
Classifier: Framework :: AsyncIO
Classifier: Intended Audience :: Developers
Classifier: Intended Audience :: Education
Classifier: Intended Audience :: Science/Research
Classifier: License :: Other/Proprietary License
Classifier: Natural Language :: English
Classifier: Operating System :: OS Independent
Classifier: Programming Language :: Python :: 3
Classifier: Programming Language :: Python :: 3.12
Classifier: Topic :: Scientific/Engineering
Classifier: Topic :: Scientific/Engineering :: GIS
Classifier: Typing :: Typed
Project-URL: Repository, https://github.com/IgnaciodelaTorreArias/natnet-client
